g42cloudsdkims/__init__.py
g42cloudsdkims/v2/__init__.py
g42cloudsdkims/v2/ims_async_client.py
g42cloudsdkims/v2/ims_client.py
g42cloudsdkims/v2/model/__init__.py
g42cloudsdkims/v2/model/add_image_tag_request.py
g42cloudsdkims/v2/model/add_image_tag_request_body.py
g42cloudsdkims/v2/model/add_image_tag_response.py
g42cloudsdkims/v2/model/add_or_update_tags_request_body.py
g42cloudsdkims/v2/model/additional_properties.py
g42cloudsdkims/v2/model/batch_add_members_request.py
g42cloudsdkims/v2/model/batch_add_members_request_body.py
g42cloudsdkims/v2/model/batch_add_members_response.py
g42cloudsdkims/v2/model/batch_add_or_delete_tags_request.py
g42cloudsdkims/v2/model/batch_add_or_delete_tags_request_body.py
g42cloudsdkims/v2/model/batch_add_or_delete_tags_response.py
g42cloudsdkims/v2/model/batch_delete_members_request.py
g42cloudsdkims/v2/model/batch_delete_members_response.py
g42cloudsdkims/v2/model/batch_update_members_request.py
g42cloudsdkims/v2/model/batch_update_members_request_body.py
g42cloudsdkims/v2/model/batch_update_members_response.py
g42cloudsdkims/v2/model/copy_image_cross_region_request.py
g42cloudsdkims/v2/model/copy_image_cross_region_request_body.py
g42cloudsdkims/v2/model/copy_image_cross_region_response.py
g42cloudsdkims/v2/model/copy_image_in_region_request.py
g42cloudsdkims/v2/model/copy_image_in_region_request_body.py
g42cloudsdkims/v2/model/copy_image_in_region_response.py
g42cloudsdkims/v2/model/create_data_image.py
g42cloudsdkims/v2/model/create_data_image_request.py
g42cloudsdkims/v2/model/create_data_image_request_body.py
g42cloudsdkims/v2/model/create_data_image_response.py
g42cloudsdkims/v2/model/create_image_request.py
g42cloudsdkims/v2/model/create_image_request_body.py
g42cloudsdkims/v2/model/create_image_response.py
g42cloudsdkims/v2/model/create_or_update_tags_request.py
g42cloudsdkims/v2/model/create_or_update_tags_response.py
g42cloudsdkims/v2/model/create_whole_image_request.py
g42cloudsdkims-0.0.10b0.dist-info/LICENSE
g42cloudsdkims-0.0.10b0.dist-info/METADATA
g42cloudsdkims-0.0.10b0.dist-info/WHEEL
g42cloudsdkims-0.0.10b0.dist-info/top_level.txt
g42cloudsdkims-0.0.10b0.dist-info/RECORD
